fn_graph/__init__.py
fn_graph/caches.py
fn_graph/calculation.py
fn_graph/examples/__init__.py
fn_graph/examples/broken.py
fn_graph/examples/caching.py
fn_graph/examples/car_savings.py
fn_graph/examples/credit.py
fn_graph/examples/credit_data.csv
fn_graph/examples/finance.py
fn_graph/examples/machine_learning.py
fn_graph/examples/namespaces.py
fn_graph/examples/plotting.py
fn_graph/examples/share_prices.csv
fn_graph/examples/shares_in_issue.csv
fn_graph/examples/stock_market.py
fn_graph/profiler.py
fn_graph/tests/__init__.py
fn_graph/tests/large_graph.py
fn_graph/tests/test_basics.py
fn_graph/tests/test_cache_methods.py
fn_graph/tests/test_links.py
fn_graph/tests/utils.py
fn_graph/usage.py
fn_graph-0.14.3.dist-info/WHEEL
fn_graph-0.14.3.dist-info/METADATA
fn_graph-0.14.3.dist-info/RECORD
