Metadata-Version: 2.1
Name: fn-graph
Version: 0.14.3
Summary: Manage, maintain and reuse complex function graphs without the hassle.
Home-page: https://github.com/BusinessOptics/fn_graph
License: MIT
Author: James Saunders
Author-email: james@businessoptics.biz
Requires-Python: >=3.7,<4.0
Classifier: License :: OSI Approved :: MIT License
Classifier: Programming Language :: Python :: 3
Classifier: Programming Language :: Python :: 3.7
Classifier: Programming Language :: Python :: 3.8
Classifier: Programming Language :: Python :: 3.9
Provides-Extra: examples
Requires-Dist: graphviz (>=0.13.2,<0.14.0)
Requires-Dist: littleutils (>=0.2.1,<0.3.0)
Requires-Dist: matplotlib; extra == "examples"
Requires-Dist: networkx (>=2.4,<3.0)
Requires-Dist: pandas; extra == "examples"
Requires-Dist: plotly; extra == "examples"
Requires-Dist: seaborn; extra == "examples"
Requires-Dist: sklearn; extra == "examples"
Requires-Dist: statsmodels; extra == "examples"
Requires-Dist: yfinance; extra == "examples"
Project-URL: Documentation, https://fn-graph.readthedocs.io/
Project-URL: Repository, https://github.com/BusinessOptics/fn_graph
